llm_stream_parser/__init__.py
llm_stream_parser/models.py
llm_stream_parser/parser.py
llm_stream_parser/py.typed
llm_stream_parser-0.1.1.data/data/llm_stream_parser/py.typed
llm_stream_parser-0.1.1.dist-info/METADATA
llm_stream_parser-0.1.1.dist-info/WHEEL
llm_stream_parser-0.1.1.dist-info/licenses/LICENSE
llm_stream_parser-0.1.1.dist-info/RECORD
