Metadata-Version: 2.4
Name: llm-stream-parser
Version: 0.1.1
Summary: Real-time parser for LLM streaming responses with tag-based content extraction
Project-URL: Homepage, https://github.com/AriesYB/llm-stream-parser
Project-URL: Documentation, https://github.com/AriesYB/llm-stream-parser#readme
Project-URL: Repository, https://github.com/AriesYB/llm-stream-parser
Project-URL: Issues, https://github.com/AriesYB/llm-stream-parser/issues
Author-email: HetFrame <yangbiao.yangbiao@qq.com>
License: MIT
License-File: LICENSE
Keywords: ai,llm,nlp,parser,stream,streaming,tag-parser
Classifier: Development Status :: 4 - Beta
Classifier: Intended Audience :: Developers
Classifier: License :: OSI Approved :: MIT License
Classifier: Programming Language :: Python :: 3
Classifier: Programming Language :: Python :: 3.8
Classifier: Programming Language :: Python :: 3.9
Classifier: Programming Language :: Python :: 3.10
Classifier: Programming Language :: Python :: 3.11
Classifier: Programming Language :: Python :: 3.12
Classifier: Topic :: Scientific/Engineering :: Artificial Intelligence
Classifier: Topic :: Software Development :: Libraries :: Python Modules
Classifier: Topic :: Text Processing :: Linguistic
Requires-Python: >=3.8
Requires-Dist: pydantic>=2.0.0
Requires-Dist: pytest-asyncio>=0.24.0
Requires-Dist: pytest>=8.3.5
Provides-Extra: dev
Requires-Dist: black>=23.0.0; extra == 'dev'
Requires-Dist: mypy>=1.0.0; extra == 'dev'
Requires-Dist: pytest-asyncio>=0.21.0; extra == 'dev'
Requires-Dist: pytest-cov>=4.0.0; extra == 'dev'
Requires-Dist: pytest>=7.0.0; extra == 'dev'
Requires-Dist: ruff>=0.1.0; extra == 'dev'
